<?xml version="1.0" encoding="UTF-8"?>
<properties>
<comment>Properties for JFritz v0.7.2.31.4</comment>
<entry key="FILTER_DATE_END">11.11.11 11:11</entry>
<entry key="FILTER_DATE_START">11.11.11 11:11</entry>
<entry key="callerTable.column.callbycall.width">70</entry>
<entry key="callerTable.column.comment.width">135</entry>
<entry key="callerTable.column.date.width">85</entry>
<entry key="callerTable.column.duration.width">60</entry>
<entry key="callerTable.column.number.width">185</entry>
<entry key="callerTable.column.participant.width">242</entry>
<entry key="callerTable.column.picture.width">50</entry>
<entry key="callerTable.column.port.width">115</entry>
<entry key="callerTable.column.route.width">80</entry>
<entry key="callerTable.column.type.width">35</entry>
<entry key="callerTable.column0.name">type</entry>
<entry key="callerTable.column1.name">date</entry>
<entry key="callerTable.column2.name">callbycall</entry>
<entry key="callerTable.column3.name">number</entry>
<entry key="callerTable.column4.name">picture</entry>
<entry key="callerTable.column5.name">participant</entry>
<entry key="callerTable.column6.name">port</entry>
<entry key="callerTable.column7.name">route</entry>
<entry key="callerTable.column8.name">duration</entry>
<entry key="callerTable.column9.name">comment</entry>
<entry key="callmessenger.popup.xpos">415</entry>
<entry key="callmessenger.popup.ypos">374</entry>
<entry key="configDialog.height">470</entry>
<entry key="configDialog.width">700</entry>
<entry key="date_filter.special"></entry>
<entry key="filter_callbycall">0</entry>
<entry key="filter_callin">0</entry>
<entry key="filter_callinfailed">0</entry>
<entry key="filter_callout">0</entry>
<entry key="filter_comment">0</entry>
<entry key="filter_date">0</entry>
<entry key="filter_fixed">0</entry>
<entry key="filter_handy">0</entry>
<entry key="filter_number">0</entry>
<entry key="filter_search">0</entry>
<entry key="filter_search.text"></entry>
<entry key="filter_sip">0</entry>
<entry key="filter_sip_providers"> </entry>
<entry key="inet.monitoring">true</entry>
<entry key="position.height">1010</entry>
<entry key="position.left">-8</entry>
<entry key="position.top">-8</entry>
<entry key="position.width">1296</entry>
<entry key="window.state">1</entry>
<entry key="window.state.old">6</entry>
</properties>
